uidgen/__init__.py
uidgen/__main__.py
uidgen/data.py
uidgen-1.0.2.dist-info/METADATA
uidgen-1.0.2.dist-info/WHEEL
uidgen-1.0.2.dist-info/licenses/LICENSE
uidgen-1.0.2.dist-info/RECORD
