Metadata-Version: 2.3
Name: uidgen
Version: 1.0.2
Summary: An adjective-noun-number identifier generator.
Project-URL: homepage, https://github.com/jaymody/uidgen
Project-URL: repository, https://github.com/jaymody/uidgen
Author-email: Jay Mody <jaykmody@gmail.com>
License: MIT License
License-File: LICENSE
Keywords: names,random,rng
Classifier: License :: OSI Approved :: MIT License
Classifier: Natural Language :: English
Classifier: Operating System :: OS Independent
Classifier: Programming Language :: Python :: 3
Requires-Python: >=3.6
